README.md
setup.cfg
setup.py
julabo/__init__.py
julabo/connection.py
julabo/device.py
julabo/protocol.py
julabo/simulator.py
julabo.egg-info/PKG-INFO
julabo.egg-info/SOURCES.txt
julabo.egg-info/dependency_links.txt
julabo.egg-info/entry_points.txt
julabo.egg-info/requires.txt
julabo.egg-info/top_level.txt
julabo/tango/__init__.py
julabo/tango/server/__init__.py
julabo/tango/server/device.py