Metadata-Version: 2.1
Name: julabo
Version: 2.2.0
Summary: julabo library
Home-page: https://github.com/tiagocoutinho/julabo
Author: Tiago Coutinho
Author-email: tcoutinho@cells.es
License: LGPLv3
Project-URL: Documentation, https://github.com/tiagocoutinho/julabo
Project-URL: Source, https://github.com/tiagocoutinho/julabo
Keywords: julabo,library,tango
Platform: UNKNOWN
Classifier: Natural Language :: English
Classifier: Intended Audience :: Developers
Classifier: Development Status :: 2 - Pre-Alpha
Classifier: Programming Language :: Python :: 3
Classifier: Programming Language :: Python :: 3.5
Classifier: Programming Language :: Python :: 3.6
Classifier: Programming Language :: Python :: 3.7
Classifier: Programming Language :: Python :: 3.8
Classifier: License :: OSI Approved :: GNU Lesser General Public License v3 or later (LGPLv3+)
Provides-Extra: tango
Provides-Extra: simulator
